<?xml version="1.0" encoding="iso8859-1"?><ProcesosEIAC xsi:schemaLocation="http://www.tirea.es/EIAC/ProcesosEIAC ProcesosEIAC.xsd" xmlns="http://www.tirea.es/EIAC/ProcesosEIAC" xmlns:xsi="http://www.w3.org/2001/XMLSchema-instance"><Objetos><Siniestro><DatosPoliza><Mediador><Email>jose.perez@fuengirolabrokers.com</Email><Nombre>FUENGIROLA-FUENGIROLA BROKERS</Nombre><Telefono>952469935</Telefono></Mediador><IdPoliza>00000124490962</IdPoliza><FechaEfecto>10/06/2022</FechaEfecto><CodigoEntidad><CodigoInterno>Zurich Insurance PLC</CodigoInterno><CodigoDGS>C0133</CodigoDGS></CodigoEntidad><DatosRamo><DescripcionRamo>0054100001HOGAR GO]</DescripcionRamo></DatosRamo><OtrosDatos><DatosTomador><nif>27388446T</nif><razonSocial>SUIZA,0023,MIJAS</razonSocial><telefono></telefono></DatosTomador></OtrosDatos></DatosPoliza><DatosSiniestro><IdSiniestroEntidad>0217549187</IdSiniestroEntidad><FechaDeclaracion>15/11/2022 11:27:59</FechaDeclaracion><FechaOcurrencia>04/10/2022</FechaOcurrencia><PosicionSiniestro></PosicionSiniestro><SituacionesSiniestro><Situacion><NumeroOrden></NumeroOrden><SituacionSiniestro></SituacionSiniestro><FechaSituacion></FechaSituacion></Situacion></SituacionesSiniestro><DescripcionSiniestro>daños por agua en techo de baño</DescripcionSiniestro><AccionesSiniestro><Accion><AccionSiniestro></AccionSiniestro><FechaAccion></FechaAccion><DescripcionAccion></DescripcionAccion></Accion></AccionesSiniestro><LugarSiniestro><NombreVia>AV  SUIZA</NombreVia><Telefono>630229390</Telefono><Contacto></Contacto><Email>amoyanoa1@hotmail.com - </Email><CodigoPostal>AV  SUIZA</CodigoPostal><Poblacion>CALA DE MIJAS, LA</Poblacion><Provincia>MIJAS</Provincia></LugarSiniestro><RiesgosSiniestro><RiesgoRecSin><DescripcionRiesgo>daños por agua en techo de baño</DescripcionRiesgo><Version>daños por agua en techo de baño</Version></RiesgoRecSin></RiesgosSiniestro><riesgosPoliza><riesgo><direccion></direccion></riesgo></riesgosPoliza><FigurasSiniestro><FiguraSiniestro><Nombre></Nombre><Telefono></Telefono></FiguraSiniestro></FigurasSiniestro></DatosSiniestro></Siniestro></Objetos></ProcesosEIAC>