<?xml version="1.0" encoding="iso8859-1"?><ProcesosEIAC xsi:schemaLocation="http://www.tirea.es/EIAC/ProcesosEIAC ProcesosEIAC.xsd" xmlns="http://www.tirea.es/EIAC/ProcesosEIAC" xmlns:xsi="http://www.w3.org/2001/XMLSchema-instance"><Objetos><Siniestro><DatosPoliza><Mediador><Email>edwin@insurance-masters.com</Email><Nombre>MARBELLA-FRANKEN 1</Nombre><Telefono>952863402</Telefono></Mediador><IdPoliza>00000118892397</IdPoliza><FechaEfecto>09/08/2021</FechaEfecto><CodigoEntidad><CodigoInterno>Zurich Insurance PLC</CodigoInterno><CodigoDGS>C0133</CodigoDGS></CodigoEntidad><DatosRamo><DescripcionRamo>0054100001HOGAR GO]</DescripcionRamo></DatosRamo><OtrosDatos><DatosTomador><nif>Y2582946Z</nif><razonSocial>MAGIAZA,0067,RIOGORD</razonSocial><telefono></telefono></DatosTomador></OtrosDatos></DatosPoliza><DatosSiniestro><IdSiniestroEntidad>0217546191</IdSiniestroEntidad><FechaDeclaracion>31/01/2023 11:04:32</FechaDeclaracion><FechaOcurrencia>04/10/2022</FechaOcurrencia><PosicionSiniestro></PosicionSiniestro><SituacionesSiniestro><Situacion><NumeroOrden></NumeroOrden><SituacionSiniestro></SituacionSiniestro><FechaSituacion></FechaSituacion></Situacion></SituacionesSiniestro><DescripcionSiniestro>EXCESO DE CONSUMO DE AGUA</DescripcionSiniestro><AccionesSiniestro><Accion><AccionSiniestro></AccionSiniestro><FechaAccion></FechaAccion><DescripcionAccion></DescripcionAccion></Accion></AccionesSiniestro><LugarSiniestro><NombreVia>PG  MAGIAZA</NombreVia><Telefono></Telefono><Contacto></Contacto><Email>keeskuit@hotmail.com - </Email><CodigoPostal>PG  MAGIAZA</CodigoPostal><Poblacion>RIOGORDO</Poblacion><Provincia>RIOGORDO</Provincia></LugarSiniestro><RiesgosSiniestro><RiesgoRecSin><DescripcionRiesgo>EXCESO DE CONSUMO DE AGUA</DescripcionRiesgo><Version>EXCESO DE CONSUMO DE AGUA</Version></RiesgoRecSin></RiesgosSiniestro><riesgosPoliza><riesgo><direccion></direccion></riesgo></riesgosPoliza><FigurasSiniestro><FiguraSiniestro><Nombre>SERVIHOGAR</Nombre><Telefono></Telefono></FiguraSiniestro></FigurasSiniestro></DatosSiniestro></Siniestro></Objetos></ProcesosEIAC>